airflow_waterdrop_plugin/__init__.py
airflow_waterdrop_plugin/_version.py
airflow_waterdrop_plugin/operators/__init__.py
airflow_waterdrop_plugin/operators/waterdrop_operator.py
airflow_waterdrop_plugin-0.1.0.dist-info/LICENSE
airflow_waterdrop_plugin-0.1.0.dist-info/METADATA
airflow_waterdrop_plugin-0.1.0.dist-info/WHEEL
airflow_waterdrop_plugin-0.1.0.dist-info/top_level.txt
airflow_waterdrop_plugin-0.1.0.dist-info/RECORD
